zope.app.schema-5.0-py3.9-nspkg.pth
zope/app/schema/README.rst
zope/app/schema/__init__.py
zope/app/schema/configure.zcml
zope/app/schema/tests.py
zope/app/schema/vocabulary.py
zope/app/schema/zope.app.schema-configure.zcml
zope.app.schema-5.0.dist-info/LICENSE.txt
zope.app.schema-5.0.dist-info/METADATA
zope.app.schema-5.0.dist-info/WHEEL
zope.app.schema-5.0.dist-info/namespace_packages.txt
zope.app.schema-5.0.dist-info/top_level.txt
zope.app.schema-5.0.dist-info/RECORD
